.DS_Store
pyvdj/__init__.py
pyvdj/add_clone_count.py
pyvdj/add_gt_n.py
pyvdj/add_obs.py
pyvdj/diversity.py
pyvdj/find_clones.py
pyvdj/get_spec.py
pyvdj/graph_cdr3.py
pyvdj/load_vdj.py
pyvdj/read10xsummary.py
pyvdj/stats.py
pyvdj-0.1.1.dist-info/LICENSE
pyvdj-0.1.1.dist-info/METADATA
pyvdj-0.1.1.dist-info/WHEEL
pyvdj-0.1.1.dist-info/top_level.txt
pyvdj-0.1.1.dist-info/RECORD
