Metadata-Version: 2.1
Name: pyvdj
Version: 0.1.1
Summary: V(D)J sequencing data analysis
Home-page: https://github.com/veghp/pyVDJ
Author: Peter Vegh
Author-email: peter.vegh@newcastle.ac.uk
License: UNKNOWN
Platform: UNKNOWN
Classifier: Programming Language :: Python :: 3
Classifier: License :: OSI Approved :: GNU General Public License v3 or later (GPLv3+)
Classifier: Operating System :: OS Independent
Requires-Dist: pandas
Requires-Dist: anndata
